{
  "project_info": {
    "project_number": "642481884636",
    "firebase_url": "https://sns-project2-1a952.firebaseio.com",
    "project_id": "sns-project2-1a952",
    "storage_bucket": "sns-project2-1a952.appspot.com"
  },
  "client": [
    {
      "client_info": {
        "mobilesdk_app_id": "1:642481884636:android:e4130e67ff5becc429d319",
        "android_client_info": {
          "package_name": "com.example.sns_project2"
        }
      },
      "oauth_client": [
        {
          "client_id": "642481884636-krjqtdcobtc2b3a6lsv9ehsc38jstsdu.apps.googleusercontent.com",
          "client_type": 3
        }
      ],
      "api_key": [
        {
          "current_key": "AIzaSyA_aXdkcaoTrv9DZBiA-RYtW1YIercZQtY"
        }
      ],
      "services": {
        "appinvite_service": {
          "other_platform_oauth_client": [
            {
              "client_id": "642481884636-krjqtdcobtc2b3a6lsv9ehsc38jstsdu.apps.googleusercontent.com",
              "client_type": 3
            }
          ]
        }
      }
    }
  ],
  "configuration_version": "1"
}